tail_recursive/__init__.py
tail_recursive-2.1.0.dist-info/LICENSE
tail_recursive-2.1.0.dist-info/WHEEL
tail_recursive-2.1.0.dist-info/METADATA
tail_recursive-2.1.0.dist-info/RECORD
