Metadata-Version: 2.1
Name: tail-recursive
Version: 2.1.0
Summary: Tail recursion with a simple decorator api.
Home-page: https://github.com/0scarB/tail-recursive
License: MIT
Author: 0scarB
Author-email: oscarb@protonmail.com
Requires-Python: >=3.8,<4.0
Classifier: License :: OSI Approved :: MIT License
Classifier: Programming Language :: Python :: 3
Classifier: Programming Language :: Python :: 3.10
Classifier: Programming Language :: Python :: 3.8
Classifier: Programming Language :: Python :: 3.9
Classifier: Topic :: Software Development
Project-URL: Documentation, https://github.com/0scarB/tail-recursive
Project-URL: Repository, https://github.com/0scarB/tail-recursive
